pyktl/__init__.py
pyktl/pyktl.py
PyKTL-0.3.8.dist-info/LICENSE
PyKTL-0.3.8.dist-info/METADATA
PyKTL-0.3.8.dist-info/WHEEL
PyKTL-0.3.8.dist-info/top_level.txt
PyKTL-0.3.8.dist-info/RECORD
