Metadata-Version: 2.1
Name: PyKTL
Version: 0.3.8
Summary: This library provides utility methods to generate and sign Knox Cloud Tokens using python.
Home-page: https://github.com/mattintech/PyKTL
Author: Matt Hills
Author-email: Matt Hills <mattintech@gmail.com>
Project-URL: Homepage, https://github.com/mattintech/PyKTL
Project-URL: Issues, https://github.com/mattintech/PyKTL/issues
Classifier: Programming Language :: Python :: 3
Classifier: License :: OSI Approved :: MIT License
Classifier: Operating System :: OS Independent
Requires-Python: >=3.8
License-File: LICENSE
Requires-Dist: PyJWT
Requires-Dist: pycryptodome
Requires-Dist: cryptography
